{
    "id": "birthday-today",
    "title": {
      "en": "When someone's birthday is today",
      "nl": "Wanneer iemand jarig is vandaag",
      "de": "Wenn heute jemand Geburtstag hat",
      "fr": "Quand c'est l'anniversaire de quelqu'un aujourd'hui",
      "it": "Quando è il compleanno di qualcuno oggi",
      "es": "Cuando es el cumpleaños de alguien hoy",
      "sv": "När någons födelsedag är idag",
      "no": "Når noen har bursdag i dag",
      "da": "Når nogen har fødselsdag i dag",
      "ru": "Когда у кого-то сегодня день рождения",
      "pl": "Kiedy ktoś ma dzisiaj urodziny"
    },
    "tokens": [
      {
        "name": "name",
        "type": "string",
        "title": {
          "en": "Birthday person",
          "nl": "Naam jarige",
          "de": "Geburtstagskind",
          "fr": "Personne qui fête son anniversaire",
          "it": "Persona festeggiata",
          "es": "Persona de cumpleaños",
          "sv": "Födelsedagsbarn",
          "no": "Bursdagsbarn",
          "da": "Fødselar",
          "ru": "Имя именинника",
          "pl": "Osoba obchodząca urodziny"
        },
        "example": {
          "en": "Jon Doe",
          "nl": "Jon Doe",
          "de": "Max Mustermann",
          "fr": "Jean Dupont",
          "it": "Mario Rossi",
          "es": "María Pérez",
          "sv": "Anna Andersson",
          "no": "Per Olsen",
          "da": "Lise Nielsen",
          "ru": "Иван Иванов",
          "pl": "Jan Kowalski"
        }
      },
      {
        "name": "mobile",
        "type": "string",
        "title": {
          "en": "Mobile number",
          "nl": "Telefoonnummer",
          "de": "Handynummer",
          "fr": "Numéro de téléphone mobile",
          "it": "Numero di telefono cellulare",
          "es": "Número de teléfono móvil",
          "sv": "Mobilnummer",
          "no": "Mobilnummer",
          "da": "Mobilnummer",
          "ru": "Мобильный номер",
          "pl": "Numer telefonu komórkowego"
        },
        "example": {
          "en": "+31612345678",
          "nl": "+31612345678",
          "de": "+4916012345678",
          "fr": "+33123456789",
          "it": "+391234567890",
          "es": "+34123456789",
          "sv": "+46123456789",
          "no": "+47123456789",
          "da": "+45123456789",
          "ru": "+79123456789",
          "pl": "+48123456789"
        }
      },
      {
        "name": "message",
        "type": "string",
        "title": {
          "en": "Birthday message",
          "nl": "Verjaardagsbericht",
          "de": "Geburtstagsnachricht",
          "fr": "Message d'anniversaire",
          "it": "Messaggio di compleanno",
          "es": "Mensaje de cumpleaños",
          "sv": "Födelsedagshälsning",
          "no": "Bursdagsmelding",
          "da": "Fødselsdagshilsen",
          "ru": "Поздравление с днем рождения",
          "pl": "Wiadomość urodzinowa"
        },
        "example": {
          "en": "Happy B-day!",
          "nl": "Gefeliciteerd!",
          "de": "Herzlichen Glückwunsch zum Geburtstag!",
          "fr": "Joyeux anniversaire!",
          "it": "Buon compleanno!",
          "es": "¡Feliz cumpleaños!",
          "sv": "Grattis på födelsedagen!",
          "no": "Gratulerer med dagen!",
          "da": "Tillykke med fødselsdagen!",
          "ru": "С днем рождения!",
          "pl": "Wszystkiego najlepszego!"
        }
      },
      {
        "name": "age",
        "type": "number",
        "title": {
          "en": "Age",
          "nl": "Leeftijd",
          "de": "Alter",
          "fr": "Âge",
          "it": "Età",
          "es": "Edad",
          "sv": "Ålder",
          "no": "Alder",
          "da": "Alder",
          "ru": "Возраст",
          "pl": "Wiek"
        },
        "example": {
          "en": "38",
          "nl": "38",
          "de": "38",
          "fr": "38",
          "it": "38",
          "es": "38",
          "sv": "38",
          "no": "38",
          "da": "38",
          "ru": "38",
          "pl": "38"
        }
      }
    ]
  }
  